tian_hramony_mcp/__init__.py
tian_hramony_mcp-1.0.0.dist-info/WHEEL
tian_hramony_mcp-1.0.0.dist-info/entry_points.txt
tian_hramony_mcp-1.0.0.dist-info/METADATA
tian_hramony_mcp-1.0.0.dist-info/RECORD
