Metadata-Version: 2.3
Name: tian-hramony-mcp
Version: 1.0.0
Summary: 鸿蒙开发文档MCP
Author: 孤单的城
Author-email: 孤单的城 <10196842+tianlangaa@user.noreply.gitee.com>
Requires-Dist: mcp[cli]>=1.24.0
Requires-Python: >=3.13
